bspump/__init__.py
bspump/__main__.py
bspump/__version__.py
bspump/application.py
bspump/exception.py
bspump/fileloader.py
bspump/pipeline.py
bspump/pumpbuilder.py
bspump/service.py
bspump/abc/__init__.py
bspump/abc/anomaly.py
bspump/abc/connection.py
bspump/abc/generator.py
bspump/abc/lookup.py
bspump/abc/lookupprovider.py
bspump/abc/processor.py
bspump/abc/sink.py
bspump/abc/source.py
bspump/aggregation/__init__.py
bspump/aggregation/hyperloglog.py
bspump/amqp/__init__.py
bspump/amqp/connection.py
bspump/amqp/sink.py
bspump/amqp/source.py
bspump/analyzer/__init__.py
bspump/analyzer/analyzer.py
bspump/analyzer/analyzingsource.py
bspump/analyzer/geoanalyzer.py
bspump/analyzer/latch.py
bspump/analyzer/sessionanalyzer.py
bspump/analyzer/threshold.py
bspump/analyzer/timedriftanalyzer.py
bspump/analyzer/timewindowanalyzer.py
bspump/anomaly/__init__.py
bspump/anomaly/analyzer.py
bspump/anomaly/generalanomaly.py
bspump/anomaly/manager.py
bspump/anomaly/storage.py
bspump/avro/__init__.py
bspump/avro/deserializer.py
bspump/avro/loader.py
bspump/avro/serializer.py
bspump/avro/sink.py
bspump/avro/source.py
bspump/cache/__init__.py
bspump/cache/cachedict.py
bspump/cache/lrucachedict.py
bspump/common/__init__.py
bspump/common/aggregator.py
bspump/common/bytes.py
bspump/common/flatten.py
bspump/common/hexlify.py
bspump/common/iterator.py
bspump/common/json.py
bspump/common/jsonbytes.py
bspump/common/mapping.py
bspump/common/null.py
bspump/common/print.py
bspump/common/routing.py
bspump/common/tee.py
bspump/common/time.py
bspump/common/transfr.py
bspump/crypto/__init__.py
bspump/crypto/aes.py
bspump/crypto/hashing.py
bspump/declarative/__init__.py
bspump/declarative/abc.py
bspump/declarative/builder.py
bspump/declarative/declerror.py
bspump/declarative/dot.py
bspump/declarative/generator.py
bspump/declarative/libraries.py
bspump/declarative/optimizer.py
bspump/declarative/processor.py
bspump/declarative/segmentbuilder.py
bspump/declarative/timewindowanalyzer.py
bspump-21.11.dist-info/LICENSE
bspump-21.11.dist-info/METADATA
bspump-21.11.dist-info/WHEEL
bspump-21.11.dist-info/top_level.txt
bspump-21.11.dist-info/RECORD
