Metadata-Version: 2.1
Name: bspump
Version: 21.11
Summary: BSPump is a real-time stream processor for Python 3.6+
Home-page: https://github.com/LibertyAces/BitSwanPump
Author: TeskaLabs Ltd
Author-email: info@teskalabs.com
License: BSD License
Project-URL: Source, https://github.com/LibertyAces/BitSwanPump
Platform: any
Classifier: Development Status :: 5 - Production/Stable
Classifier: Programming Language :: Python :: 3.6
Classifier: Programming Language :: Python :: 3.7
License-File: LICENSE
Requires-Dist: asab (>=21.11)
Requires-Dist: aiohttp (>=3.6.2)
Requires-Dist: requests (>=2.24.0)
Requires-Dist: aiokafka (>=0.7.0)
Requires-Dist: aiozk (>=0.25.0)
Requires-Dist: aiosmtplib (>=1.1.3)
Requires-Dist: fastavro (>=0.23.5)
Requires-Dist: google-api-python-client (>=1.7.10)
Requires-Dist: numpy (>=1.19.0)
Requires-Dist: pika (>=1.1.0)
Requires-Dist: pymysql (<=0.9.2,>=0.9.2)
Requires-Dist: aiomysql (>=0.0.20)
Requires-Dist: mysql-replication (>=0.21)
Requires-Dist: pytz (>=2020.1)
Requires-Dist: netaddr (>=0.7.20)
Requires-Dist: pyyaml (>=5.4)
Requires-Dist: pymongo (>=3.10.1)
Requires-Dist: motor (>=2.1.0)
Requires-Dist: mongoquery (>=1.3.6)
Requires-Dist: pybind11 (>=2.6.1)
Requires-Dist: cysimdjson (==21.11b2)
Requires-Dist: pywinrm (>=0.4.1)
Requires-Dist: pandas (>=0.24.2)
Requires-Dist: xxhash (>=1.4.4)
Requires-Dist: orjson (>=3.4.7)
Requires-Dist: dataclasses (>=0.5) ; python_version < "3.7"
